telebirr/__init__.py
telebirr/telebirr.py
telebirr/utils.py
telebirr-0.1.11.dist-info/METADATA
telebirr-0.1.11.dist-info/WHEEL
telebirr-0.1.11.dist-info/top_level.txt
telebirr-0.1.11.dist-info/RECORD
