Metadata-Version: 2.1
Name: telebirr
Version: 0.1.11
Summary: Telebirr integration
Author: Eba Alemayehu
Author-email: <ebaalemayhu3@gmail.com>
Keywords: python,telebirr,payment,ethiopia,ethio telecom
Classifier: Development Status :: 1 - Planning
Classifier: Intended Audience :: Developers
Classifier: Programming Language :: Python :: 3
Classifier: Operating System :: Unix
Classifier: Operating System :: MacOS :: MacOS X
Classifier: Operating System :: Microsoft :: Windows
